bash_like/__init__.py
bash_like/py.typed
bash_like-0.1.2.dist-info/LICENSE
bash_like-0.1.2.dist-info/METADATA
bash_like-0.1.2.dist-info/WHEEL
bash_like-0.1.2.dist-info/top_level.txt
bash_like-0.1.2.dist-info/RECORD
