Metadata-Version: 2.1
Name: bash-like
Version: 0.1.2
Summary: A small utility library to handle arguments and read/write text to files using bash-like syntax
Home-page: https://github.com/seanbreckenridge/bash_like
Author: Sean Breckenridge
Author-email: seanbrecke@gmail.com
License: http://www.apache.org/licenses/LICENSE-2.0
Keywords: shell file
Platform: UNKNOWN
Classifier: License :: OSI Approved :: Apache Software License
Classifier: Programming Language :: Python
Classifier: Programming Language :: Python :: 3
Classifier: Programming Language :: Python :: 3.6
Classifier: Programming Language :: Python :: 3.7
Classifier: Programming Language :: Python :: 3.8
Classifier: Programming Language :: Python :: 3.9
Provides-Extra: testing
Requires-Dist: pytest ; extra == 'testing'
Requires-Dist: mypy ; extra == 'testing'
